<http-page executeResourcesDynamically="false" name="/footer.html"
    playRequestsSequentially="false"
    recordedArtifactZipFileName="team/vus/@sock@shop - @browse - @tosca__psb1/%resources%/recorded-artifacts/0388c0d5-b9a3-4f24-865f-a29e08d4f0f1.zip"
    slaProfileEnabled="false" thinkTime="0"
    thinkTimeMode="MODE_SIMPLE_THINK_TIME" thinkTimeRangeEnd=""
    thinkTimeRangeStart="" uid="0388c0d5-b9a3-4f24-865f-a29e08d4f0f1">
    <embedded-action>9a39f159-6cd9-4586-8b2c-48cfc62225cf</embedded-action>
    <embedded-action>02ff0561-f370-4ce7-9afe-3eae55fa2692</embedded-action>
</http-page>
<http-action actionType="1" contentType="text/html; charset=UTF-8"
    eTag="W/&quot;c64-15af0a320b8&quot;" extractorInjectPathPolicy="2"
    extractorPathPolicy="1" followRedirects="false"
    generatedByClient="false"
    lastModified="Tue, 21 Mar 2017 11:31:47 GMT"
    linkExtractorSeveralMatchOccurrence="1"
    linkExtractorSeveralMatchPolicy="1" linkExtractorType="6"
    method="GET" name="/footer.html" path="/footer.html" postType="2"
    recordedArtifactZipFileName="team/vus/@sock@shop - @browse - @tosca__psb1/%resources%/recorded-artifacts/0388c0d5-b9a3-4f24-865f-a29e08d4f0f1.zip"
    recordedResponseCode="200" responseSize="3172" serverUid="front-end"
    slaProfileEnabled="false" slaProfileName="fastfail"
    uid="9a39f159-6cd9-4586-8b2c-48cfc62225cf" useKeepAlive="false">
    <responsePageFileDescription>recorded-responses/res_53500edf-8fe0-4f5b-b8f0-733c27a8883e.html</responsePageFileDescription>
    <requestContentFileDescription>recorded-requests/req_53500edf-8fe0-4f5b-b8f0-733c27a8883e.txt</requestContentFileDescription>
    <header name="Accept" value="text/html, */*; q=0.01"/>
    <header name="Accept-Encoding" value="gzip, deflate"/>
    <header name="Accept-Language" value="en-US,en;q=0.9"/>
    <header name="Cookie" value="md.sid=s%3AeYQfdJdo10l73k4Zay5whlyVR2I4rs3n.r6hlYzAdqlz7pKvw0SbqrxFHuDcXYfP5KkvHxMjLelI"/>
    <header name="Host" value="sockshop.neotys.perfreleng.org"/>
    <header name="If-Modified-Since" value="Tue, 21 Mar 2017 11:31:47 GMT"/>
    <header name="If-None-Match" value="W/&quot;c64-15af0a320b8&quot;"/>
    <header name="Proxy-Connection" value="keep-alive"/>
    <header name="Referer" value="http://sockshop.neotys.perfreleng.org/category.html"/>
    <header name="User-Agent" value="Mozilla/5.0 (Windows NT 10.0; Win64; x64) AppleWebKit/537.36 (KHTML, like Gecko) Chrome/89.0.4389.90 Safari/537.36"/>
    <header name="X-Requested-With" value="XMLHttpRequest"/>
    <responseHeaders>HTTP/1.1 200 OK&#xd;
X-Powered-By: Express&#xd;
Accept-Ranges: bytes&#xd;
Cache-Control: public, max-age=0&#xd;
Last-Modified: Tue, 21 Mar 2017 11:31:47 GMT&#xd;
ETag: W/"c64-15af0a320b8"&#xd;
Content-Type: text/html; charset=UTF-8&#xd;
Content-Length: 3172&#xd;
Date: Mon, 22 Mar 2021 15:17:06 GMT&#xd;
Connection: keep-alive</responseHeaders>
    <record-html-infos extractorRegExp="false" htmlType="0"/>
</http-action>
<http-action actionType="1" extractorInjectPathPolicy="2"
    extractorPathPolicy="1" followRedirects="false"
    generatedByClient="false" linkExtractorSeveralMatchOccurrence="1"
    linkExtractorSeveralMatchPolicy="1" linkExtractorType="6"
    method="GET" name="/catalogue" path="/catalogue" postType="2"
    recordedArtifactZipFileName="team/vus/@sock@shop - @browse - @tosca__psb1/%resources%/recorded-artifacts/0388c0d5-b9a3-4f24-865f-a29e08d4f0f1.zip"
    recordedResponseCode="200" responseSize="0" serverUid="front-end"
    slaProfileEnabled="false" slaProfileName="fastfail"
    uid="02ff0561-f370-4ce7-9afe-3eae55fa2692" useKeepAlive="false">
    <responsePageFileDescription>recorded-responses/res_02ff0561-f370-4ce7-9afe-3eae55fa2692</responsePageFileDescription>
    <requestContentFileDescription>recorded-requests/req_17e5579e-d047-44c5-b485-2670f6ed9b84.txt</requestContentFileDescription>
    <parameter encodeName="true" encodeValue="true" name="page"
        recordRawValue="1" separator="=" value="1" valueMode="USE_VALUE"/>
    <parameter encodeName="true" encodeValue="true" name="size"
        recordRawValue="6" separator="=" value="6" valueMode="USE_VALUE"/>
    <parameter encodeName="true" encodeValue="true" name="tags"
        recordRawValue="" separator="=" value="" valueMode="USE_VALUE"/>
    <header name="Accept" value="application/json, text/javascript, */*; q=0.01"/>
    <header name="Accept-Encoding" value="gzip, deflate"/>
    <header name="Accept-Language" value="en-US,en;q=0.9"/>
    <header name="Cookie" value="md.sid=s%3AeYQfdJdo10l73k4Zay5whlyVR2I4rs3n.r6hlYzAdqlz7pKvw0SbqrxFHuDcXYfP5KkvHxMjLelI"/>
    <header name="Host" value="sockshop.neotys.perfreleng.org"/>
    <header name="Proxy-Connection" value="keep-alive"/>
    <header name="Referer" value="http://sockshop.neotys.perfreleng.org/category.html"/>
    <header name="User-Agent" value="Mozilla/5.0 (Windows NT 10.0; Win64; x64) AppleWebKit/537.36 (KHTML, like Gecko) Chrome/89.0.4389.90 Safari/537.36"/>
    <header name="X-Requested-With" value="XMLHttpRequest"/>
    <responseHeaders>HTTP/1.1 200 OK&#xd;
X-Powered-By: Express&#xd;
Date: Mon, 22 Mar 2021 15:17:06 GMT&#xd;
Connection: keep-alive&#xd;
Transfer-Encoding: chunked</responseHeaders>
    <record-html-infos extractorRegExp="false" htmlType="0"/>
</http-action>
