<http-page executeResourcesDynamically="false" name="/navbar.html_1"
    playRequestsSequentially="false"
    recordedArtifactZipFileName="team/vus/@sock@shop - @many @transactions/%resources%/recorded-artifacts/73cdf693-f6c8-4de4-bfb1-2b77116e2e9f.zip"
    slaProfileEnabled="false" thinkTime="0"
    thinkTimeMode="MODE_SIMPLE_THINK_TIME" thinkTimeRangeEnd=""
    thinkTimeRangeStart="" uid="73cdf693-f6c8-4de4-bfb1-2b77116e2e9f">
    <embedded-action>5f95f983-3e70-4cbb-81b9-6a5633fa7052</embedded-action>
    <embedded-action>75709cb0-d354-4476-8936-9e589c743231</embedded-action>
    <embedded-action>58b19259-55a9-424c-9709-274a8dfb36a2</embedded-action>
</http-page>
<http-action actionType="1" contentType="text/html; charset=UTF-8"
    eTag="W/&quot;29e8-15af0a320b8&quot;" extractorInjectPathPolicy="2"
    extractorPathPolicy="1" followRedirects="false"
    generatedByClient="false"
    lastModified="Tue, 21 Mar 2017 11:31:47 GMT"
    linkExtractorSeveralMatchOccurrence="1"
    linkExtractorSeveralMatchPolicy="1" linkExtractorType="6"
    method="GET" name="/navbar.html" path="/navbar.html" postType="2"
    recordedArtifactZipFileName="team/vus/@sock@shop - @many @transactions/%resources%/recorded-artifacts/73cdf693-f6c8-4de4-bfb1-2b77116e2e9f.zip"
    recordedResponseCode="200" responseSize="10728"
    serverUid="sockshop.neotys.perfreleng.org" slaProfileEnabled="false"
    slaProfileName="fastfail" uid="5f95f983-3e70-4cbb-81b9-6a5633fa7052" useKeepAlive="false">
    <responsePageFileDescription>recorded-responses/res_db85b775-c331-47ed-9fa6-f1772239c276.html</responsePageFileDescription>
    <requestContentFileDescription>recorded-requests/req_db85b775-c331-47ed-9fa6-f1772239c276.txt</requestContentFileDescription>
    <header name="Accept" value="text/html, */*; q=0.01"/>
    <header name="Accept-Encoding" value="gzip, deflate"/>
    <header name="Accept-Language" value="en-US,en;q=0.9"/>
    <header name="Cookie" value="md.sid=s%3ApnpWhsT6tLjSDx1B1sEWKnbIe-foS-pu.%2FbeKdSd8BrbrZmVqRB4GSJ5s1IY6AEAWHQNAzuB7qXE"/>
    <header name="Host" value="sockshop.neotys.perfreleng.org"/>
    <header name="If-Modified-Since" value="Tue, 21 Mar 2017 11:31:47 GMT"/>
    <header name="If-None-Match" value="W/&quot;29e8-15af0a320b8&quot;"/>
    <header name="Proxy-Connection" value="keep-alive"/>
    <header name="Referer" value="http://sockshop.neotys.perfreleng.org/category.html"/>
    <header name="User-Agent" value="Mozilla/5.0 (Windows NT 10.0; Win64; x64) AppleWebKit/537.36 (KHTML, like Gecko) Chrome/89.0.4389.90 Safari/537.36"/>
    <header name="X-Requested-With" value="XMLHttpRequest"/>
    <responseHeaders>HTTP/1.1 200 OK&#xd;
X-Powered-By: Express&#xd;
Accept-Ranges: bytes&#xd;
Cache-Control: public, max-age=0&#xd;
Last-Modified: Tue, 21 Mar 2017 11:31:47 GMT&#xd;
ETag: W/"29e8-15af0a320b8"&#xd;
Content-Type: text/html; charset=UTF-8&#xd;
Content-Length: 10728&#xd;
Date: Tue, 23 Mar 2021 12:48:21 GMT&#xd;
Connection: keep-alive</responseHeaders>
    <record-html-infos extractorRegExp="false" htmlType="0"/>
</http-action>
<http-action actionType="1" contentType="image/png"
    eTag="W/&quot;2123-15af0a320b8&quot;" extractorInjectPathPolicy="2"
    extractorPathPolicy="1" followRedirects="false"
    generatedByClient="false"
    lastModified="Tue, 21 Mar 2017 11:31:47 GMT"
    linkExtractorSeveralMatchOccurrence="1"
    linkExtractorSeveralMatchPolicy="1" linkExtractorType="6"
    method="GET" name="/img/logo.png" path="/img/logo.png" postType="2"
    recordedArtifactZipFileName="team/vus/@sock@shop - @many @transactions/%resources%/recorded-artifacts/73cdf693-f6c8-4de4-bfb1-2b77116e2e9f.zip"
    recordedResponseCode="200" responseSize="0"
    serverUid="sockshop.neotys.perfreleng.org" slaProfileEnabled="false"
    slaProfileName="fastfail" uid="75709cb0-d354-4476-8936-9e589c743231" useKeepAlive="false">
    <requestContentFileDescription>recorded-requests/req_6485875d-bcbe-4434-83b7-e48d78db9c50.txt</requestContentFileDescription>
    <header name="Accept" value="image/avif,image/webp,image/apng,image/svg+xml,image/*,*/*;q=0.8"/>
    <header name="Accept-Encoding" value="gzip, deflate"/>
    <header name="Accept-Language" value="en-US,en;q=0.9"/>
    <header name="Cookie" value="md.sid=s%3ApnpWhsT6tLjSDx1B1sEWKnbIe-foS-pu.%2FbeKdSd8BrbrZmVqRB4GSJ5s1IY6AEAWHQNAzuB7qXE"/>
    <header name="Host" value="sockshop.neotys.perfreleng.org"/>
    <header name="If-Modified-Since" value="Tue, 21 Mar 2017 11:31:47 GMT"/>
    <header name="If-None-Match" value="W/&quot;2123-15af0a320b8&quot;"/>
    <header name="Proxy-Connection" value="keep-alive"/>
    <header name="Referer" value="http://sockshop.neotys.perfreleng.org/category.html"/>
    <header name="User-Agent" value="Mozilla/5.0 (Windows NT 10.0; Win64; x64) AppleWebKit/537.36 (KHTML, like Gecko) Chrome/89.0.4389.90 Safari/537.36"/>
    <responseHeaders>HTTP/1.1 200 OK&#xd;
X-Powered-By: Express&#xd;
Accept-Ranges: bytes&#xd;
Cache-Control: public, max-age=0&#xd;
Last-Modified: Tue, 21 Mar 2017 11:31:47 GMT&#xd;
ETag: W/"2123-15af0a320b8"&#xd;
Content-Type: image/png&#xd;
Content-Length: 8483&#xd;
Date: Tue, 23 Mar 2021 12:48:21 GMT&#xd;
Connection: keep-alive</responseHeaders>
    <record-html-infos extractorRegExp="false" htmlType="0"/>
</http-action>
<http-action actionType="1" contentType="image/png"
    eTag="W/&quot;2123-15af0a320b8&quot;" extractorInjectPathPolicy="2"
    extractorPathPolicy="1" followRedirects="false"
    generatedByClient="false"
    lastModified="Tue, 21 Mar 2017 11:31:47 GMT"
    linkExtractorSeveralMatchOccurrence="1"
    linkExtractorSeveralMatchPolicy="1" linkExtractorType="6"
    method="GET" name="/img/logo-small.png" path="/img/logo-small.png"
    postType="2"
    recordedArtifactZipFileName="team/vus/@sock@shop - @many @transactions/%resources%/recorded-artifacts/73cdf693-f6c8-4de4-bfb1-2b77116e2e9f.zip"
    recordedResponseCode="200" responseSize="0"
    serverUid="sockshop.neotys.perfreleng.org" slaProfileEnabled="false"
    slaProfileName="fastfail" uid="58b19259-55a9-424c-9709-274a8dfb36a2" useKeepAlive="false">
    <requestContentFileDescription>recorded-requests/req_04c33e32-b81a-43ba-b1f4-fd9fd678c08d.txt</requestContentFileDescription>
    <header name="Accept" value="image/avif,image/webp,image/apng,image/svg+xml,image/*,*/*;q=0.8"/>
    <header name="Accept-Encoding" value="gzip, deflate"/>
    <header name="Accept-Language" value="en-US,en;q=0.9"/>
    <header name="Cookie" value="md.sid=s%3ApnpWhsT6tLjSDx1B1sEWKnbIe-foS-pu.%2FbeKdSd8BrbrZmVqRB4GSJ5s1IY6AEAWHQNAzuB7qXE"/>
    <header name="Host" value="sockshop.neotys.perfreleng.org"/>
    <header name="If-Modified-Since" value="Tue, 21 Mar 2017 11:31:47 GMT"/>
    <header name="If-None-Match" value="W/&quot;2123-15af0a320b8&quot;"/>
    <header name="Proxy-Connection" value="keep-alive"/>
    <header name="Referer" value="http://sockshop.neotys.perfreleng.org/category.html"/>
    <header name="User-Agent" value="Mozilla/5.0 (Windows NT 10.0; Win64; x64) AppleWebKit/537.36 (KHTML, like Gecko) Chrome/89.0.4389.90 Safari/537.36"/>
    <responseHeaders>HTTP/1.1 200 OK&#xd;
X-Powered-By: Express&#xd;
Accept-Ranges: bytes&#xd;
Cache-Control: public, max-age=0&#xd;
Last-Modified: Tue, 21 Mar 2017 11:31:47 GMT&#xd;
ETag: W/"2123-15af0a320b8"&#xd;
Content-Type: image/png&#xd;
Content-Length: 8483&#xd;
Date: Tue, 23 Mar 2021 12:48:21 GMT&#xd;
Connection: keep-alive</responseHeaders>
    <record-html-infos extractorRegExp="false" htmlType="0"/>
</http-action>
